<?xml version="1.0" encoding="UTF-8" standalone="yes"?>
<addon id="skin.tetradui" version="1.0.0" name="TetradUI" provider-name="Jezz_X, TeamUI">
  <requires>
    <import addon="xbmc.gui" version="5.15.00" />
	<import addon="script.embuary.helper" version="2.0.2"/>
  </requires>
  <extension point="xbmc.gui.skin" defaultthemename="textures.xbt" debugging="false" effectslowdown="1.0">
    <res width="1280" height="720" aspect="16:9" default="true" folder="xml" />
  </extension>
  <extension point="xbmc.addon.metadata">
    <platform>all</platform>
    <license>Creative Commons Attribution-Share Alike 3.0 United States</license>
    <forum>https://forum.kodi.tv/forumdisplay.php?fid=182</forum>
    <website>https://kodi.wiki/view/Add-on:TetradUI</website>
    <source>https://github.com/gade01/skin.tetradui</source>
    <assets>
      <icon>resources/icon.png</icon>
      <fanart>resources/fanart.jpg</fanart>
      <screenshot>resources/screenshot-01.jpg</screenshot>
      <screenshot>resources/screenshot-02.jpg</screenshot>
      <screenshot>resources/screenshot-03.jpg</screenshot>
      <screenshot>resources/screenshot-04.jpg</screenshot>
      <screenshot>resources/screenshot-05.jpg</screenshot>
      <screenshot>resources/screenshot-06.jpg</screenshot>
      <screenshot>resources/screenshot-07.jpg</screenshot>
      <screenshot>resources/screenshot-08.jpg</screenshot>
      <screenshot>resources/screenshot-09.jpg</screenshot>
      <screenshot>resources/screenshot-10.jpg</screenshot>
    </assets>
    <news>[B]1.0.0[/B][CR]- Alpha version</news>
    <description lang="en_GB">TetradUI is a skin add-on for Kodi media center. TetradUI is based on JX720 by Jezz_X.[CR]This add-on was created by TeamUI.</description>
    <summary lang="en_GB">TetradUI is a skin add-on for Kodi media center</summary>
  </extension>
</addon>